arrowspace/__init__.py
arrowspace/arrowspace.cpython-313-darwin.so
arrowspace-0.24.12.dist-info/METADATA
arrowspace-0.24.12.dist-info/WHEEL
arrowspace-0.24.12.dist-info/licenses/LICENSE
arrowspace-0.24.12.dist-info/RECORD
