Metadata-Version: 2.4
Name: arrowspace
Version: 0.24.12
Classifier: Programming Language :: Rust
Classifier: Programming Language :: Python :: Implementation :: CPython
Classifier: Programming Language :: Python :: Implementation :: PyPy
Classifier: Development Status :: 4 - Beta
Classifier: Intended Audience :: Developers
Classifier: Intended Audience :: Science/Research
Classifier: Topic :: Scientific/Engineering
Classifier: Topic :: Scientific/Engineering :: Artificial Intelligence
Classifier: Topic :: Scientific/Engineering :: Information Analysis
Classifier: Topic :: Software Development :: Libraries :: Python Modules
Classifier: Topic :: Database :: Front-Ends
Classifier: Programming Language :: Python
Classifier: Programming Language :: Python :: 3
Classifier: Programming Language :: Python :: 3 :: Only
Classifier: Programming Language :: Python :: 3.9
Classifier: Programming Language :: Python :: 3.10
Classifier: Programming Language :: Python :: 3.11
Classifier: Programming Language :: Python :: 3.12
Classifier: Programming Language :: Python :: 3.13
Classifier: Programming Language :: Rust
Classifier: Operating System :: OS Independent
License-File: LICENSE
Summary: Python bindings for ArrowSpace (Rust) providing graph-based similarity search, signal graphs, and spectral methods for vector data.
Keywords: vector-search,spectral-analysis,graph-signal,similarity-search,machine-learning
Home-Page: https://github.com/tuned-org-uk/pyarrowspace
License-Expression: MIT OR Apache-2.0
Requires-Python: >=3.12
Project-URL: Homepage, https://github.com/tuned-org-uk/pyarrowspace
Project-URL: Repository, https://github.com/tuned-org-uk/pyarrowspace.git
